memoryllm/__init__.py
memoryllm-0.1.1.dist-info/licenses/LICENSE
memoryllm-0.1.1.dist-info/METADATA
memoryllm-0.1.1.dist-info/WHEEL
memoryllm-0.1.1.dist-info/top_level.txt
memoryllm-0.1.1.dist-info/RECORD
